{
  "project_info": {
    "project_number": "892021988060",
    "project_id": "stayfresh-36edf",
    "storage_bucket": "stayfresh-36edf.firebasestorage.app"
  },
  "client": [
    {
      "client_info": {
        "mobilesdk_app_id": "1:892021988060:android:1d14c491862826971f7219",
        "android_client_info": {
          "package_name": "com.example.stayfresh"
        }
      },
      "oauth_client": [],
      "api_key": [
        {
          "current_key": "AIzaSyCiQp4Bamtmi7FADS-bFbZZoPPqC4-2GEM"
        }
      ],
      "services": {
        "appinvite_service": {
          "other_platform_oauth_client": []
        }
      }
    }
  ],
  "configuration_version": "1"
}